pindo/__init__.py
pindo/code.py
pindo/lang.py
pindo/runner.py
pindo/exception/__init__.py
pindo/exception/code_failed_to_run.py
pindo/exception/invalid_runtime_version.py
pindo/runtime/__init__.py
pindo/runtime/docker/__init__.py
pindo/runtime/docker/c.py
pindo/runtime/docker/cplus.py
pindo/runtime/docker/elixir.py
pindo/runtime/docker/engine.py
pindo/runtime/docker/go.py
pindo/runtime/docker/java.py
pindo/runtime/docker/php.py
pindo/runtime/docker/python.py
pindo/runtime/docker/ruby.py
pindo/runtime/docker/rust.py
pindo-1.2.0.dist-info/LICENSE.txt
pindo-1.2.0.dist-info/METADATA
pindo-1.2.0.dist-info/WHEEL
pindo-1.2.0.dist-info/top_level.txt
pindo-1.2.0.dist-info/RECORD
