Metadata-Version: 2.1
Name: pindo
Version: 1.2.0
Summary: Securely Build and Run Code in Docker.
Home-page: https://github.com/clivern/pindo/
Author: Clivern
Author-email: hello@clivern.com
License: MIT
Project-URL: Documentation, https://github.com/clivern/pindo/
Project-URL: Source, https://github.com/clivern/pindo/
Project-URL: Changelog, https://github.com/Clivern/Pindo/blob/main/CHANGELOG.rst
Project-URL: Tracker, https://github.com/Clivern/Pindo/issues
Project-URL: Download, https://pypi.org/project/Pindo/#files
Platform: any
Classifier: Development Status :: 5 - Production/Stable
Classifier: Programming Language :: Python
Classifier: License :: OSI Approved :: MIT License
License-File: LICENSE.txt
Requires-Dist: docker
Requires-Dist: importlib-metadata ; python_version < "3.8"
Provides-Extra: testing
Requires-Dist: docker ; extra == 'testing'
Requires-Dist: setuptools ; extra == 'testing'
Requires-Dist: pytest ; extra == 'testing'
Requires-Dist: pytest-cov ; extra == 'testing'
